DESCRIPTION.rst
MANIFEST.in
setup.py
HoroscopeGenerator.egg-info/PKG-INFO
HoroscopeGenerator.egg-info/SOURCES.txt
HoroscopeGenerator.egg-info/dependency_links.txt
HoroscopeGenerator.egg-info/requires.txt
HoroscopeGenerator.egg-info/top_level.txt
horoscope_generator/HoroscopeGenerator.py
horoscope_generator/__init__.py
horoscope_generator/data/.grammar.txt.swp
horoscope_generator/data/grammar.txt