Metadata-Version: 1.1
Name: HoroscopeGenerator
Version: 0.1.8
Summary: Generates horoscopes
Home-page: https://github.com/mouse-reeve/horoscope-generator
Author: Mouse Reeve
Author-email: mouse.reeve@gmail.com
License: MIT
Keywords: generative language astrology horoscopes context-free grammar
Platform: UNKNOWN
Classifier: Development Status :: 3 - Alpha
Classifier: Intended Audience :: Developers
Classifier: Topic :: Artistic Software
Classifier: License :: OSI Approved :: MIT License
Classifier: Programming Language :: Python :: 2
Classifier: Programming Language :: Python :: 2.7
